{"meta":{"name":"USA","id":"TV-cool68","type":"channel","posterShape":"landscape","videos":[{"id":"TV-coolstream_68_0","title":"USA - ABC Atlanta"},{"id":"TV-coolstream_68_1","title":"USA - ABC Chicago"},{"id":"TV-coolstream_68_2","title":"USA - ABC Houston"},{"id":"TV-coolstream_68_3","title":"USA - ABC Los Angeles"},{"id":"TV-coolstream_68_4","title":"USA - ABC Miami"},{"id":"TV-coolstream_68_5","title":"USA - ABC New York"},{"id":"TV-coolstream_68_6","title":"USA - ABC New York HD"},{"id":"TV-coolstream_68_7","title":"USA - ACC Network HD"},{"id":"TV-coolstream_68_8","title":"USA - ACCN ESPN HD"},{"id":"TV-coolstream_68_9","title":"USA - AMC Movie HD"},{"id":"TV-coolstream_68_10","title":"USA - Animal Planet HD"},{"id":"TV-coolstream_68_11","title":"USA - Baby TV HD"},{"id":"TV-coolstream_68_12","title":"USA - BBC America HD"},{"id":"TV-coolstream_68_13","title":"USA - Bravo West HD"},{"id":"TV-coolstream_68_14","title":"USA - Cartoon Network HD"},{"id":"TV-coolstream_68_15","title":"USA - CBS Boston"},{"id":"TV-coolstream_68_16","title":"USA - CBS Chicago"},{"id":"TV-coolstream_68_17","title":"USA - CBS Chicago HD"},{"id":"TV-coolstream_68_18","title":"USA - CBS Houston"},{"id":"TV-coolstream_68_19","title":"USA - CBS Los Angeles"},{"id":"TV-coolstream_68_20","title":"USA - CBS Los Angeles HD"},{"id":"TV-coolstream_68_21","title":"USA - CBS Miami"},{"id":"TV-coolstream_68_22","title":"USA - CBS Miami HD"},{"id":"TV-coolstream_68_23","title":"USA - CBS New York"},{"id":"TV-coolstream_68_24","title":"USA - CBS San Diego"},{"id":"TV-coolstream_68_25","title":"USA - CBS San Francisco"},{"id":"TV-coolstream_68_26","title":"USA - CBS San Francisco HD"},{"id":"TV-coolstream_68_27","title":"USA - CBS Sports Network"},{"id":"TV-coolstream_68_28","title":"USA - CBS Texas"},{"id":"TV-coolstream_68_29","title":"USA - CBS Texas HD"},{"id":"TV-coolstream_68_30","title":"USA - Cinemax HD"},{"id":"TV-coolstream_68_31","title":"USA - CNBC"},{"id":"TV-coolstream_68_32","title":"USA - CNN HD"},{"id":"TV-coolstream_68_33","title":"USA - Cooking Channel HD"},{"id":"TV-coolstream_68_34","title":"USA - Destination America HD"},{"id":"TV-coolstream_68_35","title":"USA - Discovery Channel HD"},{"id":"TV-coolstream_68_36","title":"USA - Discovery Life HD"},{"id":"TV-coolstream_68_37","title":"USA - Discovery Science HD"},{"id":"TV-coolstream_68_38","title":"USA - Discovery Velocity HD"},{"id":"TV-coolstream_68_39","title":"USA - Disney Channel HD"},{"id":"TV-coolstream_68_40","title":"USA - Disney Jr HD"},{"id":"TV-coolstream_68_41","title":"USA - Disney XD HD"},{"id":"TV-coolstream_68_42","title":"USA - DIY Network HD"},{"id":"TV-coolstream_68_43","title":"USA - DIY Network HD"},{"id":"TV-coolstream_68_44","title":"USA - E! Enterteiment HD"},{"id":"TV-coolstream_68_45","title":"USA - Epix Hits HD"},{"id":"TV-coolstream_68_46","title":"USA - ESPN 2 HD"},{"id":"TV-coolstream_68_47","title":"USA - ESPN Deportes HD"},{"id":"TV-coolstream_68_48","title":"USA - ESPN Deportes HD"},{"id":"TV-coolstream_68_49","title":"USA - ESPN HD"},{"id":"TV-coolstream_68_50","title":"USA - ESPN U HD"},{"id":"TV-coolstream_68_51","title":"USA - ESPN Xtra HD"},{"id":"TV-coolstream_68_52","title":"USA - Food Network HD"},{"id":"TV-coolstream_68_53","title":"USA - FOX 11 Dallas"},{"id":"TV-coolstream_68_54","title":"USA - FOX 5 Atlanta HD"},{"id":"TV-coolstream_68_55","title":"USA - FOX Boston"},{"id":"TV-coolstream_68_56","title":"USA - Fox Business HD"},{"id":"TV-coolstream_68_57","title":"USA - Fox Bussines Network"},{"id":"TV-coolstream_68_58","title":"USA - FOX Chicago"},{"id":"TV-coolstream_68_59","title":"USA - Fox College Sports Atlantic HD"},{"id":"TV-coolstream_68_60","title":"USA - Fox College Sports Central HD"},{"id":"TV-coolstream_68_61","title":"USA - Fox College Sports Pacific HD"},{"id":"TV-coolstream_68_62","title":"USA - FOX Dallas"},{"id":"TV-coolstream_68_63","title":"USA - Fox Deportes HD"},{"id":"TV-coolstream_68_64","title":"USA - FOX Detroit"},{"id":"TV-coolstream_68_65","title":"USA - FOX Kansas City"},{"id":"TV-coolstream_68_66","title":"USA - FOX Los Angeles"},{"id":"TV-coolstream_68_67","title":"USA - Fox Los Angeles HD"},{"id":"TV-coolstream_68_68","title":"USA - FOX Miami"},{"id":"TV-coolstream_68_69","title":"USA - Fox New York HD"},{"id":"TV-coolstream_68_70","title":"USA - Fox News Channel"},{"id":"TV-coolstream_68_71","title":"USA - Fox Phoenix HD"},{"id":"TV-coolstream_68_72","title":"USA - Fox Soccer Plus HD"},{"id":"TV-coolstream_68_73","title":"USA - Fox Sports 1 HD"},{"id":"TV-coolstream_68_74","title":"USA - Fox Sports 2 HD"},{"id":"TV-coolstream_68_75","title":"USA - Fox Sports Arizona HD"},{"id":"TV-coolstream_68_76","title":"USA - Fox Sports North Carolinas HD"},{"id":"TV-coolstream_68_77","title":"USA - Fox Sports Ohio HD"},{"id":"TV-coolstream_68_78","title":"USA - Fox Sports Oklahoma HD"},{"id":"TV-coolstream_68_79","title":"USA - Fox Sports Prime Ticket HD"},{"id":"TV-coolstream_68_80","title":"USA - Fox Sports Southeast HD"},{"id":"TV-coolstream_68_81","title":"USA - Fox Sports Sportime Ohio HD"},{"id":"TV-coolstream_68_82","title":"USA - Fox Sports Sun HD"},{"id":"TV-coolstream_68_83","title":"USA - Fox Sports Tenessee HD"},{"id":"TV-coolstream_68_84","title":"USA - Fox Sports Wisconsin HD"},{"id":"TV-coolstream_68_85","title":"USA - FOX Washington HD"},{"id":"TV-coolstream_68_86","title":"USA - FreeForm HD"},{"id":"TV-coolstream_68_87","title":"USA - Fusion HD"},{"id":"TV-coolstream_68_88","title":"USA - FX HD"},{"id":"TV-coolstream_68_89","title":"USA - FXM HD"},{"id":"TV-coolstream_68_90","title":"USA - FXX HD"},{"id":"TV-coolstream_68_91","title":"USA - Golf HD"},{"id":"TV-coolstream_68_92","title":"USA - H2 HD"},{"id":"TV-coolstream_68_93","title":"USA - Hallmark  HD"},{"id":"TV-coolstream_68_94","title":"USA - Hallmark Drama HD"},{"id":"TV-coolstream_68_95","title":"USA - Hallmark Movies & Mysteries HD"},{"id":"TV-coolstream_68_96","title":"USA - HBO 2 HD"},{"id":"TV-coolstream_68_97","title":"USA - HBO Comedy HD"},{"id":"TV-coolstream_68_98","title":"USA - HBO HD"},{"id":"TV-coolstream_68_99","title":"USA - HBO Plus FHD"},{"id":"TV-coolstream_68_100","title":"USA - HBO Plus HD"},{"id":"TV-coolstream_68_101","title":"USA - HBO Signature HD"},{"id":"TV-coolstream_68_102","title":"USA - HBO West HD"},{"id":"TV-coolstream_68_103","title":"USA - HBO Zone HD"},{"id":"TV-coolstream_68_104","title":"USA - HGTV HD"},{"id":"TV-coolstream_68_105","title":"USA - Investigation Discovery HD"},{"id":"TV-coolstream_68_106","title":"USA - Lifetime HD"},{"id":"TV-coolstream_68_107","title":"USA - Lifetime Movies HD"},{"id":"TV-coolstream_68_108","title":"USA - MLB HD"},{"id":"TV-coolstream_68_109","title":"USA - Moremax HD"},{"id":"TV-coolstream_68_110","title":"USA - MSG HD"},{"id":"TV-coolstream_68_111","title":"USA - MSNBC HD"},{"id":"TV-coolstream_68_112","title":"USA - Nat Geo Mundo HD"},{"id":"TV-coolstream_68_113","title":"USA - Natgeo People HD"},{"id":"TV-coolstream_68_114","title":"USA - National Geographic HD"},{"id":"TV-coolstream_68_115","title":"USA - NBA Channel HD"},{"id":"TV-coolstream_68_116","title":"USA - NBC Bay Area HD"},{"id":"TV-coolstream_68_117","title":"USA - NBC California HD"},{"id":"TV-coolstream_68_118","title":"USA - NBC Chicago"},{"id":"TV-coolstream_68_119","title":"USA - NBC Chicago HD"},{"id":"TV-coolstream_68_120","title":"USA - NBC Detroit"},{"id":"TV-coolstream_68_121","title":"USA - NBC Los Angeles"},{"id":"TV-coolstream_68_122","title":"USA - NBC Miami"},{"id":"TV-coolstream_68_123","title":"USA - NBC Miami HD"},{"id":"TV-coolstream_68_124","title":"USA - NBC New Orleans"},{"id":"TV-coolstream_68_125","title":"USA - NBC New York"},{"id":"TV-coolstream_68_126","title":"USA - NBC New York HD"},{"id":"TV-coolstream_68_127","title":"USA - NBC Philadelphia HD"},{"id":"TV-coolstream_68_128","title":"USA - NBC San Diego"},{"id":"TV-coolstream_68_129","title":"USA - NBC Universo HD"},{"id":"TV-coolstream_68_130","title":"USA - NBCSN Sports"},{"id":"TV-coolstream_68_131","title":"USA - NESN Sports HD"},{"id":"TV-coolstream_68_132","title":"USA - NFL Network HD"},{"id":"TV-coolstream_68_133","title":"USA - NFL Redzone HD"},{"id":"TV-coolstream_68_134","title":"USA - NHL Network"},{"id":"TV-coolstream_68_135","title":"USA - Nick Junior HD"},{"id":"TV-coolstream_68_136","title":"USA - Nickelodeon HD"},{"id":"TV-coolstream_68_137","title":"USA - NickToons HD"},{"id":"TV-coolstream_68_138","title":"USA - Own HD"},{"id":"TV-coolstream_68_139","title":"USA - Oxygen HD"},{"id":"TV-coolstream_68_140","title":"USA - PAC Arizona HD"},{"id":"TV-coolstream_68_141","title":"USA - PAC Bay Area HD"},{"id":"TV-coolstream_68_142","title":"USA - PAC Los Angeles HD"},{"id":"TV-coolstream_68_143","title":"USA - PAC Mountain HD"},{"id":"TV-coolstream_68_144","title":"USA - PAC Network HD"},{"id":"TV-coolstream_68_145","title":"USA - PAC Washinton HD"},{"id":"TV-coolstream_68_146","title":"USA - Paramount HD"},{"id":"TV-coolstream_68_147","title":"USA - RetroPlex HD"},{"id":"TV-coolstream_68_148","title":"USA - Showtime Next HD"},{"id":"TV-coolstream_68_149","title":"USA - Stadium Sports HD"},{"id":"TV-coolstream_68_150","title":"USA - Starz Comedy HD"},{"id":"TV-coolstream_68_151","title":"USA - Starz Encore Black HD"},{"id":"TV-coolstream_68_152","title":"USA - Starz Encore Family HD"},{"id":"TV-coolstream_68_153","title":"USA - Starz Encore Suspense HD"},{"id":"TV-coolstream_68_154","title":"USA - Starz Encore West HD"},{"id":"TV-coolstream_68_155","title":"USA - Starz HD"},{"id":"TV-coolstream_68_156","title":"USA - Sundance TV HD"},{"id":"TV-coolstream_68_157","title":"USA - SyFy HD"},{"id":"TV-coolstream_68_158","title":"USA - TBS HD"},{"id":"TV-coolstream_68_159","title":"USA - TCM"},{"id":"TV-coolstream_68_160","title":"USA - TeenNick HD"},{"id":"TV-coolstream_68_161","title":"USA - Tennis Channel HD"},{"id":"TV-coolstream_68_162","title":"USA - TLC HD"},{"id":"TV-coolstream_68_163","title":"USA - TNT FHD"},{"id":"TV-coolstream_68_164","title":"USA - TNT HD"},{"id":"TV-coolstream_68_165","title":"USA - Travel TV HD"},{"id":"TV-coolstream_68_166","title":"USA - TruTV HD"},{"id":"TV-coolstream_68_167","title":"USA - TUDN SD"},{"id":"TV-coolstream_68_168","title":"USA - UFC Figth Pass FHD"},{"id":"TV-coolstream_68_169","title":"USA - UFC HD"},{"id":"TV-coolstream_68_170","title":"USA - UFC HD"},{"id":"TV-coolstream_68_171","title":"USA - Universal Kids HD"},{"id":"TV-coolstream_68_172","title":"USA - USA Network HD"},{"id":"TV-coolstream_68_173","title":"USA - We TV"},{"id":"TV-coolstream_68_174","title":"USA - World Fishing Network HD"},{"id":"TV-coolstream_68_175","title":"USA - WWE Network FHD"},{"id":"TV-coolstream_68_176","title":"USA - Yes Network HD"}]}}