{"meta":{"name":"COSTA RICA","id":"TV-cool23","type":"channel","posterShape":"landscape","videos":[{"id":"TV-coolstream_23_0","title":"Costa Rica - Canal UCR"},{"id":"TV-coolstream_23_1","title":"Costa Rica - FUTV HD"},{"id":"TV-coolstream_23_2","title":"Costa Rica - Multimedios"},{"id":"TV-coolstream_23_3","title":"Costa Rica - Repretel 11 SD"},{"id":"TV-coolstream_23_4","title":"Costa Rica - Repretel 4 SD"},{"id":"TV-coolstream_23_5","title":"Costa Rica - Repretel 6 SD"},{"id":"TV-coolstream_23_6","title":"Costa Rica - TD+ HD"},{"id":"TV-coolstream_23_7","title":"Costa Rica - TD+ 2 HD"},{"id":"TV-coolstream_23_8","title":"Costa Rica - Tele Uno SD"},{"id":"TV-coolstream_23_9","title":"Costa Rica - Teletica 7 HD"},{"id":"TV-coolstream_23_10","title":"Costa Rica - Teletica 7 SD"},{"id":"TV-coolstream_23_11","title":"Costa Rica - Tigo Sports"},{"id":"TV-coolstream_23_12","title":"Costa Rica - Tigo Sports HD"}]}}