{"meta":{"name":"MEXICO","id":"TV-cool44","type":"channel","posterShape":"landscape","videos":[{"id":"TV-coolstream_44_0","title":"Mexico - ADN 40 HD"},{"id":"TV-coolstream_44_1","title":"Mexico - AyM Sports HD"},{"id":"TV-coolstream_44_2","title":"Mexico - AZ Cinema FHD"},{"id":"TV-coolstream_44_3","title":"Mexico - AZ Click"},{"id":"TV-coolstream_44_4","title":"Mexico - AZ Corazon FHD"},{"id":"TV-coolstream_44_5","title":"Mexico - AZ Mundo FHD"},{"id":"TV-coolstream_44_6","title":"Mexico - Azteca 7 FHD"},{"id":"TV-coolstream_44_7","title":"Mexico - Azteca 7 SD"},{"id":"TV-coolstream_44_8","title":"Mexico - Azteca Uno FHD"},{"id":"TV-coolstream_44_9","title":"Mexico - Azteca Uno SD"},{"id":"TV-coolstream_44_10","title":"Mexico - Bandamax"},{"id":"TV-coolstream_44_11","title":"Mexico - BitMe"},{"id":"TV-coolstream_44_12","title":"Mexico - Canal 4 HD Guadalajara"},{"id":"TV-coolstream_44_13","title":"Mexico - Canal 5 FHD"},{"id":"TV-coolstream_44_14","title":"Mexico - Canal 66 Mexicali HD"},{"id":"TV-coolstream_44_15","title":"Mexico - Distrito Comedia FHD"},{"id":"TV-coolstream_44_16","title":"Mexico - Distrito Comedia SD"},{"id":"TV-coolstream_44_17","title":"Mexico - Estrella TV HD"},{"id":"TV-coolstream_44_18","title":"Mexico - Foro TV FHD"},{"id":"TV-coolstream_44_19","title":"Mexico - Galavision"},{"id":"TV-coolstream_44_20","title":"Mexico - Imagen TV FHD"},{"id":"TV-coolstream_44_21","title":"Mexico - Imagen TV SD"},{"id":"TV-coolstream_44_22","title":"Mexico - Ingenio TV SD"},{"id":"TV-coolstream_44_23","title":"Mexico - Las Estrellas FHD"},{"id":"TV-coolstream_44_24","title":"Mexico - Las Estrellas HD"},{"id":"TV-coolstream_44_25","title":"Mexico - Milienio Noticias"},{"id":"TV-coolstream_44_26","title":"Mexico - Multimedios Monterrey"},{"id":"TV-coolstream_44_27","title":"Mexico - ONCE Niños y Niñas"},{"id":"TV-coolstream_44_28","title":"Mexico - TV Unam SD"},{"id":"TV-coolstream_44_29","title":"Mexico - Ultra Cine HD"},{"id":"TV-coolstream_44_30","title":"Mexico - Unicable FHD"},{"id":"TV-coolstream_44_31","title":"Mexico - Unicable SD"}]}}